mlir/__init__.py
mlir/astnodes.py
mlir/dialect.py
mlir/parser.py
mlir/parser_transformer.py
mlir/visitors.py
mlir/builder/__init__.py
mlir/builder/builder.py
mlir/builder/match.py
mlir/builder/ung.py
mlir/dialects/__init__.py
mlir/dialects/affine.py
mlir/dialects/func.py
mlir/dialects/linalg.py
mlir/dialects/scf.py
mlir/dialects/standard.py
mlir/lark/mlir.lark
pymlir-0.5.dist-info/AUTHORS
pymlir-0.5.dist-info/LICENSE
pymlir-0.5.dist-info/METADATA
pymlir-0.5.dist-info/WHEEL
pymlir-0.5.dist-info/top_level.txt
pymlir-0.5.dist-info/RECORD
