Metadata-Version: 2.1
Name: pymlir
Version: 0.5
Home-page: https://github.com/spcl/pymlir
Author: SPCL @ ETH Zurich
Author-email: talbn@inf.ethz.ch
Classifier: Programming Language :: Python :: 3
Classifier: License :: OSI Approved :: BSD License
Classifier: Operating System :: OS Independent
Requires-Python: >=3.6
License-File: LICENSE
License-File: AUTHORS
Requires-Dist: lark-parser
Requires-Dist: parse
